agent_3d_summarize/__init__.py
agent_3d_summarize/apps.py
agent_3d_summarize/dataset.csv
agent_3d_summarize/djangoldp_urls.py
agent_3d_summarize/helpers.py
agent_3d_summarize/views.py
agent_3d_summarize/management/__init__.py
agent_3d_summarize/management/commands/__init__.py
agent_3d_summarize/management/commands/make_model.py
agent_dsd_summarize/__init__.py
agent_dsd_summarize/apps.py
agent_dsd_summarize/djangoldp_urls.py
agent_dsd_summarize/helpers.py
agent_dsd_summarize/views.py
agent_dsd_summarize/management/__init__.py
agent_dsd_summarize/management/commands/__init__.py
agent_dsd_summarize/management/commands/generate_dsd_mock_datas.py
agent_recommendation/3Dobjects.jsonld
agent_recommendation/__init__.py
agent_recommendation/apps.py
agent_recommendation/companies.json
agent_recommendation/djangoldp_urls.py
agent_recommendation/interactions.csv
agent_recommendation/views.py
agent_recommendation/management/commands/make_model.py
agent_search_prompt/__init__.py
agent_search_prompt/apps.py
agent_search_prompt/djangoldp_urls.py
agent_search_prompt/views.py
agent_search_prompt/management/commands/make_model.py
agent_synthesis/__init__.py
agent_synthesis/apps.py
agent_synthesis/djangoldp_urls.py
agent_synthesis/views.py
agent_synthesis/management/commands/make_model.py
djangoldp_ai_agents/__init__.py
djangoldp_ai_agents/apps.py
djangoldp_ai_agents/helpers.py
djangoldp_ai_agents/management/commands/make_model.py
djangoldp_ai_agents-2.1.4.dist-info/METADATA
djangoldp_ai_agents-2.1.4.dist-info/WHEEL
djangoldp_ai_agents-2.1.4.dist-info/top_level.txt
djangoldp_ai_agents-2.1.4.dist-info/RECORD
