Metadata-Version: 2.4
Name: djangoldp_ai_agents
Version: 2.1.4
Summary: djangoldp package for AI Agents
Home-page: https://git.startinblox.com/djangoldp-packages/djangoldp-ai-agents
Author: Startin'blox
Author-email: jbaptiste@startinblox.com
License: MIT
Classifier: Programming Language :: Python :: 3
Requires-Dist: djangoldp~=4.0.0
Requires-Dist: transformers
Requires-Dist: torch
Requires-Dist: pandas
Requires-Dist: datasets
Requires-Dist: mistralai
Requires-Dist: pydantic
Requires-Dist: numpy
Requires-Dist: onnxruntime
Requires-Dist: skl2onnx
Requires-Dist: sklearn
Provides-Extra: include-package-data
Requires-Dist: True; extra == "include-package-data"
